testforge/__init__.py
testforge/cli.py
testforge/context_fetcher.py
testforge/main.py
testforge-1.0.6.dist-info/LICENSE
testforge-1.0.6.dist-info/METADATA
testforge-1.0.6.dist-info/WHEEL
testforge-1.0.6.dist-info/entry_points.txt
testforge-1.0.6.dist-info/top_level.txt
testforge-1.0.6.dist-info/RECORD
