Metadata-Version: 2.1
Name: testforge
Version: 1.0.6
Summary: A CLI tool to generate pyton tests using AI.
Home-page: https://github.com/yourusername/testforge
Author-email: support@testforge.ai
Classifier: Programming Language :: Python :: 3
Classifier: License :: OSI Approved :: MIT License
Classifier: Operating System :: OS Independent
Requires-Python: >=3.6
License-File: LICENSE
Requires-Dist: requestsjedi
